piggies/__init__.py
piggies/master_piggy.py
piggies/piggy_btc.py
piggies/piggy_eth.py
piggies/piggy_xmr.py
piggies/processing.py
piggies-0.0.1.dist-info/METADATA
piggies-0.0.1.dist-info/RECORD
piggies-0.0.1.dist-info/WHEEL
piggies-0.0.1.dist-info/top_level.txt
