Metadata-Version: 2.1
Name: piggies
Version: 0.0.1
Summary: A package to automatically manage cryptocurrency wallets
Home-page: https://github.com/danuker/piggies
Author: Dan Gheorghe Haiduc
Author-email: danuthaiduc@gmail.com
License: MIT
Platform: UNKNOWN
Classifier: Programming Language :: Python :: 3.5
Classifier: Programming Language :: Python :: 3.6
Classifier: License :: OSI Approved :: MIT License
Classifier: Operating System :: Unix
Requires-Python: >=3.5
Requires-Dist: jsonrpclib-pelix
Requires-Dist: web3
Requires-Dist: pyetherchain
Requires-Dist: pexpect
